{"id": "21", "published": "2016-10-02T19:42:00.000+03:00", "text": "PAMPLONA, 2 Oct. (EUROPA PRESS) -    El Ayuntamiento de Pamplona ha iniciado un proceso de limpieza y saneamiento de los lagos artificiales de la ciudad. Si antes del verano se interven\u00eda en el estanque de Vistabella (Taconera) y el del Sadar (parque Orfe\u00f3n Pamplon\u00e9s ), este lunes a primera hora de la ma\u00f1ana acometer\u00e1 esa tarea en el lago de Mendillorri .\n   As\u00ed, el Ayuntamiento comenzar\u00e1 a retirar los aproximadamente 13.000 m3 de agua que alberga el estanque mediante drenaje con la ayuda de un cami\u00f3n bomba ya que, aunque se ha encontrado una v\u00e1lvula de vaciado en el fondo de estanque, nunca ha sido utilizada y se desconoce si resistir\u00e1 el proceso.\n   El agua extra\u00edda del lago se verter\u00e1 a la red de pluviales. Durante la operaci\u00f3n, que en total podr\u00eda durar tres d\u00edas, se realizar\u00e1 la captura de las especies pisc\u00edcolas mediante un procedimiento denominado 'pesca el\u00e9ctrica'. Este consiste en crear una corriente el\u00e9ctrica continua que provoca un aturdimiento temporal de los animales para facilitar su captura.\n   Tambi\u00e9n se retirar\u00e1n manualmente el centenar de gal\u00e1pagos y crust\u00e1ceos ex\u00f3ticos detectados y el resto de ejemplares de otros grupos faun\u00edsticos que aparezcan.\n   Una vez vac\u00edo, habr\u00e1 que esperar unos d\u00edas para asegurar la muerte de los huevos y larvas que pudiera haber. Luego el espacio se volver\u00e1 a rellenar con agua de la red de abastecimiento y se reintroducir\u00e1n gradualmente especies aut\u00f3ctonas (barbos, madrillas, chipas...), en un proceso de seminaturalizaci\u00f3n del lago.\n   Tambi\u00e9n se aprovechar\u00e1 para sustituir la v\u00e1lvula originaria por otra m\u00e1s accesible que permita en el futuro la limpieza del lago, simplificando la tarea y reduciendo el coste. Tras esta la operaci\u00f3n, presupuestada en 54.500 euros, se estima que el lago se mantendr\u00e1 buenas condiciones al menos durante los pr\u00f3ximos 5 a\u00f1os.\nCONTROL DE ESPECIES, LIMPIEZA Y CALIDAD DEL AGUA    El lago de Mendillorri es un estanque artificial situado en una zona verde p\u00fablica urbana cuya localizaci\u00f3n, caracter\u00edsticas y multiplicidad de usos le confieren un car\u00e1cter ambiental y social mas all\u00e1 de un estaque al uso. \n    Desde su construcci\u00f3n hace ya dos d\u00e9cadas, nunca se ha vaciado, por lo que en estos momentos no hay informaci\u00f3n sobre el estado real de sus fondos ni estimaciones sobre la cantidad de fango y residuos que pueden acumular. No se tienen datos hist\u00f3ricos sobre la calidad de sus aguas, que presumiblemente en algunos momentos del a\u00f1o puede ser baja a tenor de los indicadores puntuales que se han observado.\n   La labor de vaciado y limpieza se compagina con la necesidad de controlar las especies de car\u00e1cter ex\u00f3tico e invasor que actualmente pueblan el lago y sobre las que hay normativas que obligan a su control y erradicaci\u00f3n.\n   De la fauna que puebla el lago destacan en numero y funci\u00f3n los ejemplares de peces invasores como el lucio y la perca americana, especies depredadoras de otros peces m\u00e1s peque\u00f1os, insectos, cangrejos, anfibios e, incluso, aves. Destaca tambi\u00e9n la presencia de gal\u00e1pagos ex\u00f3ticos como la tortuga de florida que es clara competidora de las tortugas aut\u00f3ctonas que pueblan parte de r\u00edos y zonas h\u00famedas naturales de Navarra.\n   Aunque el lago se encuentra aislado parcialmente de los ecosistemas acu\u00e1ticos naturales del entorno y no es factible la colonizaci\u00f3n natural de otros ambientes, es un foco potencial de liberaci\u00f3n de especies al medio natural, bien por descuido, bien de forma intencionada, y, por tanto, un peligro para la biodiversidad.\n   Est\u00e1 ampliamente demostrado que una de las causas de p\u00e9rdida de biodiversidad viene originada por la creciente expansi\u00f3n de las especies ex\u00f3ticas invasoras, que adem\u00e1s ocasionan graves perjuicios para la econom\u00eda, en concreto, a la producci\u00f3n agr\u00edcola, ganadera y forestal, e incluso la salud p\u00fablica.", "title": "El lunes se iniciar\u00e1 el vaciado del lago de Mendillorri", "author": "EUROPA PRESS"}